<?xml version="1.0" encoding="UTF-8" standalone="yes"?>
<Actors>
    <actor>
        <actor_name>Mark Gatiss</actor_name>
        <serie>Sherlock</serie>
        <no_episodes>3</no_episodes>
    </actor>
    <actor>
        <actor_name>Louise Brealey</actor_name>
        <serie>Sherlock</serie>
        <no_episodes>3</no_episodes>
    </actor>
    <actor>
        <actor_name>Martin Freeman</actor_name>
        <serie>Sherlock</serie>
        <no_episodes>3</no_episodes>
    </actor>
    <actor>
        <actor_name>Benedict  Cumberbatch</actor_name>
        <serie>Sherlock</serie>
        <no_episodes>3</no_episodes>
    </actor>
    <actor>
        <actor_name>Amanda Abbington</actor_name>
        <serie>Sherlock</serie>
        <no_episodes>3</no_episodes>
    </actor>
    <stats>
        <no_actors>5</no_actors>
        <podium_actors>Mark Gatiss</podium_actors>
        <podium_actors>Louise Brealey</podium_actors>
        <podium_actors>Martin Freeman</podium_actors>
    </stats>
</Actors>
